dumont/__init__.py
dumont/cli.py
dumont/core.py
dumont-0.4.1.dist-info/METADATA
dumont-0.4.1.dist-info/WHEEL
dumont-0.4.1.dist-info/entry_points.txt
dumont-0.4.1.dist-info/top_level.txt
dumont-0.4.1.dist-info/RECORD
