Metadata-Version: 2.4
Name: dumont
Version: 0.4.1
Summary: Excel file generation tool with pivot tables and charts
Author: Dumont Developer
License: MIT
Project-URL: Homepage, https://github.com/tojlon/dumont
Project-URL: Repository, https://github.com/tojlon/dumont
Keywords: excel,pivot,pandas,charts,matplotlib,cli
Classifier: Development Status :: 3 - Alpha
Classifier: Intended Audience :: Developers
Classifier: License :: OSI Approved :: MIT License
Classifier: Programming Language :: Python :: 3
Classifier: Programming Language :: Python :: 3.8
Classifier: Programming Language :: Python :: 3.9
Classifier: Programming Language :: Python :: 3.10
Classifier: Programming Language :: Python :: 3.11
Classifier: Programming Language :: Python :: 3.12
Requires-Python: >=3.8
Requires-Dist: pandas>=1.5.0
Requires-Dist: xlsxwriter>=3.0.0
Requires-Dist: click>=8.0.0
Requires-Dist: openpyxl>=3.0.0
Requires-Dist: matplotlib>=3.7.0
Provides-Extra: dev
Requires-Dist: pytest>=7.0.0; extra == "dev"
Requires-Dist: black>=23.0.0; extra == "dev"
Requires-Dist: ruff>=0.1.0; extra == "dev"
